Metadata-Version: 2.1
Name: simple_query_builder
Version: 0.4
Summary: This is a small easy-to-use component for working with a database. It provides some public methods to compose SQL queries and manipulate data. Each SQL query is prepared and safe.
Home-page: https://github.com/co0lc0der/simple-query-builder-python
Download-URL: https://github.com/co0lc0der/simple-query-builder-python/archive/v0.4.zip
Author: co0lc0der
Author-email: c0der@ya.ru
License: MIT
Classifier: Topic :: Database
Classifier: Topic :: Database :: Database Engines/Servers
Classifier: License :: OSI Approved :: MIT License
Classifier: Operating System :: OS Independent
Classifier: Intended Audience :: Developers
Classifier: Programming Language :: Python
Classifier: Programming Language :: Python :: 3
Classifier: Programming Language :: Python :: 3.7
Classifier: Programming Language :: Python :: 3.8
Classifier: Programming Language :: Python :: 3.9
Classifier: Programming Language :: Python :: 3.10
Classifier: Programming Language :: Python :: 3.11
Classifier: Programming Language :: Python :: 3.12
Classifier: Programming Language :: Python :: Implementation :: PyPy
Classifier: Programming Language :: Python :: Implementation :: CPython
Classifier: Programming Language :: SQL
Classifier: Typing :: Typed
License-File: LICENSE.md
